Logic_Circuits/Full_Substrator/F_SUBS.v
module F_SUBS(A,B,C,D,E);

input A,B,C;
output D,E;
 assign D=A^B^C;
 assign E=((~(A))&C|(~(A))&B|B&C);

endmodule

Logic_Circuits/Full_Substrator/F_SUBS_tb.v
`timescale 1ns/1ns
`include "F_SUBS.v"

module F_SUBS_tb();

reg A,B,C;
wire D,E;

F_SUBS uut(A,B,C,D,E);
initial begin
  $dumpfile("F_SUBS_tb.vcd");
  $dumpvars(1,F_SUBS_tb);
  A=0;
  B=0;
  C=0;
  #20
  A=0;
  B=0;
  C=1;
  #20
  A=0;
  B=1;
  C=0;
  #20
  A=0;
  B=1;
  C=1;
  #20
  A=1;
  B=0;
  C=0;
  #20
  A=1;
  B=0;
  C=1;
  #20
  A=1;
  B=1;
  C=0;
  #20
  A=1;
  B=1;
  C=1;
  #20
  $display("Done testing");
end

endmodule

Logic_Circuits/Full_Substrator/F_SUBS_tb.vcd
$date
	Tue Oct 12 09:13:46 2021
$end
$version
	Icarus Verilog
$end
$timescale
	1ns
$end
$scope module F_SUBS_tb $end
$var wire 1 ! E $end
$var wire 1 " D $end
$var reg 1 # A $end
$var reg 1 $ B $end
$var reg 1 % C $end
$upscope $end
$enddefinitions $end
#0
$dumpvars
0%
0$
0#
0"
0!
$end
#20
1!
1"
1%
#40
0%
1$
#60
0"
1%
#80
0!
1"
0%
0$
1#
#100
0"
1%
#120
0%
1$
#140
1!
1"
1%
