Logic_Circuits/Four_Bit_C_Adder/F_ADD.v
module F_ADD(A,B,C,S,O);
input A,B,C;
output S,O;

assign S=A^B^C;
assign O=(A&B)|C&(A^B);

endmodule

Logic_Circuits/Four_Bit_C_Adder/F_ADD_tb.v
`timescale 1ns/1ns
`include "F_ADD.v"
module F_ADD_tb();
reg A,B,C;
wire S,O;
F_ADD uut(A,B,C,S,O);
initial begin
  $dumpfile("F_ADD_tb.vcd");
  $dumpvars(2,F_ADD_tb);

  A=0;
  B=0;
  C=0;
  #20
  A=0;
  B=0;
  C=1;
  #20
  A=0;
  B=1;
  C=0;
  #20
  A=0;
  B=1;
  C=1;
  #20
  A=1;
  B=0;
  C=0;
  #20
  A=1;
  B=0;
  C=1;
  #20
  A=1;
  B=1;
  C=0;
  #20
  A=1;
  B=1;
  C=1;
  #20
$display("test Done");
end

endmodule

Logic_Circuits/Four_Bit_C_Adder/F_ADD_tb.vcd
$date
	Wed Aug 09 00:38:44 2023
$end
$version
	Icarus Verilog
$end
$timescale
	1ns
$end
$scope module F_ADD_tb $end
$var wire 1 ! S $end
$var wire 1 " O $end
$var reg 1 # A $end
$var reg 1 $ B $end
$var reg 1 % C $end
$scope module uut $end
$var wire 1 # A $end
$var wire 1 $ B $end
$var wire 1 % C $end
$var wire 1 " O $end
$var wire 1 ! S $end
$upscope $end
$upscope $end
$enddefinitions $end
#0
$dumpvars
0%
0$
0#
0"
0!
$end
#20
1!
1%
#40
0%
1$
#60
1"
0!
1%
#80
0"
1!
0%
0$
1#
#100
1"
0!
1%
#120
0%
1$
#140
1!
1%
